pytest_server-1.0.1.dist-info/METADATA
pytest_server-1.0.1.dist-info/WHEEL
pytest_server-1.0.1.dist-info/entry_points.txt
pytest_server/__init__.py
pytest_server/client.py
pytest_server/pytest_server.py
pytest_server-1.0.1.dist-info/RECORD
